general_log_parser/__init__.py
general_log_parser/parser.py
general_log_parser-0.1.7.dist-info/DESCRIPTION.rst
general_log_parser-0.1.7.dist-info/entry_points.txt
general_log_parser-0.1.7.dist-info/METADATA
general_log_parser-0.1.7.dist-info/metadata.json
general_log_parser-0.1.7.dist-info/RECORD
general_log_parser-0.1.7.dist-info/top_level.txt
general_log_parser-0.1.7.dist-info/WHEEL
