Metadata-Version: 2.0
Name: general-log-parser
Version: 0.1.7
Summary: A general log parser
Home-page: https://github.com/minhhh/general-log-parser
Author: Ha.Minh
Author-email: minhhh@minhhuyha.info
License: BSD
Keywords: general-log-parser
Platform: UNKNOWN
Classifier: Development Status :: 5 - Production/Stable
Classifier: Intended Audience :: Developers
Classifier: License :: OSI Approved :: MIT License
Classifier: Natural Language :: English
Classifier: Programming Language :: Python :: 2
Classifier: Programming Language :: Python :: 2.6
Classifier: Programming Language :: Python :: 2.7
Classifier: Programming Language :: Python :: 3
Classifier: Programming Language :: Python :: 3.3
Classifier: Programming Language :: Python :: 3.4
Requires-Dist: click (==4.0)
Requires-Dist: fn (==0.4.3)
Requires-Dist: six (==1.9.0)
